flaskkits_boilerplate/__init__.py
flaskkits_boilerplate/cli.py
flaskkits_boilerplate/flaskkit.py
flaskkits_boilerplate/generator.py
flaskkits_boilerplate/helper.py
flaskkits_boilerplate/installer.py
flaskkits_boilerplate/starter/Jsvanilla-tailwind/.env
flaskkits_boilerplate/starter/Jsvanilla-tailwind/.env.example
flaskkits_boilerplate/starter/Jsvanilla-tailwind/main.py
flaskkits_boilerplate/starter/Jsvanilla-tailwind/package-lock.json
flaskkits_boilerplate/starter/Jsvanilla-tailwind/package.json
flaskkits_boilerplate/starter/Jsvanilla-tailwind/postcss.config.js
flaskkits_boilerplate/starter/Jsvanilla-tailwind/requirements.txt
flaskkits_boilerplate/starter/Jsvanilla-tailwind/tailwind.config.js
flaskkits_boilerplate/starter/Jsvanilla-tailwind/app/__init__.py
flaskkits_boilerplate/starter/Jsvanilla-tailwind/app/blueprints.py
flaskkits_boilerplate/starter/Jsvanilla-tailwind/app/extensions.py
flaskkits_boilerplate/starter/Jsvanilla-tailwind/app/controllers/counter_controller.py
flaskkits_boilerplate/starter/Jsvanilla-tailwind/app/routes/counter_routes.py
flaskkits_boilerplate/starter/Jsvanilla-tailwind/app/static/css/input.css
flaskkits_boilerplate/starter/Jsvanilla-tailwind/app/static/css/style.css
flaskkits_boilerplate/starter/Jsvanilla-tailwind/app/static/js/counter.js
flaskkits_boilerplate/starter/Jsvanilla-tailwind/app/static/js/effects.js
flaskkits_boilerplate/starter/Jsvanilla-tailwind/app/templates/base.html
flaskkits_boilerplate/starter/Jsvanilla-tailwind/app/templates/counter.html
flaskkits_boilerplate/starter/Jsvanilla-tailwind/config/__init__.py
flaskkits_boilerplate/starter/Jsvanilla-tailwind/config/default.py
flaskkits_boilerplate-0.1.5.dist-info/licenses/LICENSE
flaskkits_boilerplate-0.1.5.dist-info/METADATA
flaskkits_boilerplate-0.1.5.dist-info/WHEEL
flaskkits_boilerplate-0.1.5.dist-info/entry_points.txt
flaskkits_boilerplate-0.1.5.dist-info/top_level.txt
flaskkits_boilerplate-0.1.5.dist-info/RECORD
