Metadata-Version: 2.4
Name: flaskkits_boilerplate
Version: 0.1.5
Summary: Starter kit Flask modern dengan struktur rapi, integrasi Tailwind CSS, dan perintah CLI sederhana.
Home-page: https://github.com/lahadiyani/flaskkit
Author: Hadiani
Author-email: lahadiyani@gmail.com
License: MIT
License-File: LICENSE
Requires-Dist: Flask
Requires-Dist: Flask-SQLAlchemy
Requires-Dist: pymysql
Requires-Dist: rich
Dynamic: author
Dynamic: author-email
Dynamic: home-page
Dynamic: license
Dynamic: license-file
Dynamic: requires-dist
Dynamic: summary
